bapiparkinglot/__init__.py
bapiparkinglot/core.py
bapiparkinglot-1.0.dist-info/LICENSE.txt
bapiparkinglot-1.0.dist-info/METADATA
bapiparkinglot-1.0.dist-info/WHEEL
bapiparkinglot-1.0.dist-info/top_level.txt
bapiparkinglot-1.0.dist-info/RECORD
