Metadata-Version: 2.1
Name: bapiparkinglot
Version: 1.0
Summary: Parking Lot API dibuat untuk memenuhi syarat dalam pengerjaan soal DTO Kemenkes - Backend Engineer.
Home-page: https://github.com/bearaujus/api_parking_lot
Author: Bear Au Jus - ジュースとくま
Author-email: haryobagasasyafah6@gmail.com
License: MIT
Keywords: bapiparkinglot,DTO,Kemenkes,DTO Kemenkes,Backend Engineer
Platform: UNKNOWN
Classifier: Development Status :: 5 - Production/Stable
Classifier: Intended Audience :: Developers
Classifier: Operating System :: OS Independent
Classifier: License :: OSI Approved :: MIT License
Classifier: Programming Language :: Python :: 3.7
Classifier: Natural Language :: English
Classifier: Topic :: Utilities
Requires-Dist: flask
Requires-Dist: flask-restful
Requires-Dist: requests
